tinyq/__init__.py
tinyq/__main__.py
tinyq/app.py
tinyq/constants.py
tinyq/exceptions.py
tinyq/job.py
tinyq/queue.py
tinyq/runner.py
tinyq/task.py
tinyq/utils.py
tinyq/worker.py
tinyq-0.3.0.dist-info/DESCRIPTION.rst
tinyq-0.3.0.dist-info/METADATA
tinyq-0.3.0.dist-info/RECORD
tinyq-0.3.0.dist-info/WHEEL
tinyq-0.3.0.dist-info/entry_points.txt
tinyq-0.3.0.dist-info/metadata.json
tinyq-0.3.0.dist-info/top_level.txt
